[
  { "name": "Активия гранат", "qty": "" },
  { "name": "Активия ягоды", "qty": "" },
  { "name": "Альпро молоко Ванильное", "qty": "" },
  { "name": "Альпро молоко Кокос", "qty": "" },
  { "name": "Альпро молоко Миндаль", "qty": "" },
  { "name": "Альпро молоко Соевое", "qty": "" },
  { "name": "Ананас консервированный", "qty": "" },
  { "name": "Апельсин", "qty": "" },
  { "name": "Арахисовая паста", "qty": "" },
  { "name": "Банан", "qty": "" },
  { "name": "Батончик Нутелла б реди вафельн 22гр", "qty": "" },
  { "name": "Бисконти сет Б", "qty": "" },
  { "name": "Боржоми (Алюм.бан.0,33 )", "qty": "" },
  { "name": "Боржоми (Стекло 0,5 )", "qty": "" },
  { "name": "Боржоми стекло 0.33", "qty": "" },
  { "name": "Взбитые сливки", "qty": "" },
  { "name": "Вода Bonaqua без газа 0,5", "qty": "" },
  { "name": "Вода Bonaqua с газом 0,5л", "qty": "" },
  { "name": "Горячий Шоколад", "qty": "" },
  { "name": "Ежевика (замороженная)", "qty": "" },
  { "name": "Какао Ristora", "qty": "" },
  { "name": "Клубника (ягода) замороженная", "qty": "" },
  { "name": "Клюква (ягода)", "qty": "" },
  { "name": "КЛЮКВЕННЫЙ НАПИТОК", "qty": "" },
  { "name": "Кола 0.5", "qty": "" },
  { "name": "Кола Баночная", "qty": "" },
  { "name": "Корица Молотая", "qty": "" },
  { "name": "Кофе Lavazza", "qty": "" },
  { "name": "Кукес печенье мини сет", "qty": "" },
  { "name": "Кунжут сет Б", "qty": "" },
  { "name": "Лайм", "qty": "" },
  { "name": "ЛИМОН", "qty": "" },
  { "name": "Лимон бар", "qty": "" },
  { "name": "Малина (ягода) замороженная", "qty": "" },
  { "name": "Манжеты", "qty": "" },
  { "name": "Маршмеллоу", "qty": "" },
  { "name": "Мед 1 сорт для бара", "qty": "" },
  { "name": "Мини бисконти для кофе", "qty": "" },
  { "name": "Молоко 3,2%", "qty": "" },
  { "name": "Молоко ванильное соевое", "qty": "" },
  { "name": "Морковь Красная", "qty": "" },
  { "name": "Мороженное", "qty": "" },
  { "name": "Мохито стакан", "qty": "" },
  { "name": "Мята", "qty": "" },
  { "name": "На Вынос", "qty": "" },
  { "name": "Нутелла кг", "qty": "" },
  { "name": "Облепиха (ягода)", "qty": "" },
  { "name": "ОБЛЕПИХОВЫЙ НАПИТОК", "qty": "" },
  { "name": "Печенье \"Карамельное\"", "qty": "" },
  { "name": "Ромашка", "qty": "" },
  { "name": "Сахар", "qty": "" },
  { "name": "Сахар в пакетиках", "qty": "" },
  { "name": "Сгущенка в бутылке 1л", "qty": "" },
  { "name": "Сгущенное молоко", "qty": "" },
  { "name": "Сироп ананас Fabbri", "qty": "" },
  { "name": "Сироп арбуз Fabbri", "qty": "" },
  { "name": "Сироп банан Fabbri", "qty": "" },
  { "name": "Сироп Берри Fabri", "qty": "" },
  { "name": "Сироп ваниль Fabbri", "qty": "" },
  { "name": "Сироп гранат Fabbri", "qty": "" },
  { "name": "Сироп дыня Fabbri", "qty": "" },
  { "name": "Сироп зеленое яблоко Fabbri", "qty": "" },
  { "name": "Сироп карамель Fabbri", "qty": "" },
  { "name": "Сироп киви Fabbri", "qty": "" },
  { "name": "Сироп клубника Fabbri", "qty": "" },
  { "name": "Сироп Кокос Fabri", "qty": "" },
  { "name": "Сироп Лесной Орех Fabri", "qty": "" },
  { "name": "СИРОП МАНГО", "qty": "" },
  { "name": "Сироп манго Fabbri", "qty": "" },
  { "name": "Сироп маракуя Fabri", "qty": "" },
  { "name": "Сироп орех фундук Fabbri", "qty": "" },
  { "name": "Сироп персик Fabbri", "qty": "" },
  { "name": "Сироп Соленая карамель Fabbri", "qty": "" },
  { "name": "Сироп шоколад Fabbri", "qty": "" },
  { "name": "Сливки 11%", "qty": "" },
  { "name": "Смородина черная (замороженная)", "qty": "" },
  { "name": "Сок Piko апельсин", "qty": "" },
  { "name": "Сок Piko лесные ягоды", "qty": "" },
  { "name": "Сок Piko мультифрукт", "qty": "" },
  { "name": "Сок Piko яблочный", "qty": "" },
  { "name": "Спрайт 0,5", "qty": "" },
  { "name": "Спрайт баноч.", "qty": "" },
  { "name": "Стакан Safia 250мл одноразовый КЗ", "qty": "" },
  { "name": "Стакан Safia 330мл одноразовый КЗ", "qty": "" },
  { "name": "Стакан одноразовый 0.400мл", "qty": "" },
  { "name": "Творожный сыр хохланд", "qty": "" },
  { "name": "Топпинг- клубника GOURMET", "qty": "" },
  { "name": "Топпинг- шоколад GOURMET", "qty": "" },
  { "name": "Фанта  баноч.", "qty": "" },
  { "name": "Фанта 0,5", "qty": "" },
  { "name": "Фьюс Чай Арбуз 0.5л", "qty": "" },
  { "name": "Фьюс Чай Клубника-дыня 0.5л", "qty": "" },
  { "name": "Фьюс Чай Лесная ягода 0,5л", "qty": "" },
  { "name": "Фьюс Чай Лимон 0.5л", "qty": "" },
  { "name": "Фьюс Чай Манго-Ананас 0,5л", "qty": "" },
  { "name": "Фьюс Чай Манго-дыня 0.5л", "qty": "" },
  { "name": "Фьюс чай манго-ромашка 0.5л", "qty": "" },
  { "name": "Фьюс Чай Персик 0.5л", "qty": "" },
  { "name": "чай Tess зеленый  шт.", "qty": "" },
  { "name": "чай Tess черный шт.", "qty": "" },
  { "name": "Чай Ахмад жасмин", "qty": "" },
  { "name": "Чай Ахмад Ти ягодный в пакетиках", "qty": "" },
  { "name": "Чай зеленый Гринфилд в пакетиках", "qty": "" },
  { "name": "Чай черный Гринфилд в пакетиках", "qty": "" },
  { "name": "Чай эрел грей дилмах", "qty": "" },
  { "name": "Чебрец", "qty": "" },
  { "name": "Яблоко", "qty": "" }
]
